<?xml version="1.0" encoding="UTF-8"?><?xml-stylesheet type='text/xsl' href='_UpgradeReport_Files/UpgradeReport.xslt'?><UpgradeLog>
<Properties><Property Name="Solution" Value="FacebookAzure">
</Property><Property Name="Solution File" Value="C:\Code\FacebookAzure\FacebookAzure.sln">
</Property><Property Name="Date" Value="lundi 8 août 2011">
</Property><Property Name="Time" Value="20:46">
</Property></Properties><Event ErrorLevel="0" Project="" Source="FacebookAzure.sln" Description="File successfully backed up as C:\Code\FacebookAzure\Backup\FacebookAzure.sln">
</Event><Event ErrorLevel="0" Project="FacebookAzure" Source="FacebookAzure\FacebookAzure.csproj" Description="Project file successfully backed up as C:\Code\FacebookAzure\Backup\FacebookAzure\FacebookAzure.csproj">
</Event><Event ErrorLevel="0" Project="FacebookAzure" Source="FacebookAzure\Controllers\HomeController.cs" Description="File successfully backed up as C:\Code\FacebookAzure\Backup\FacebookAzure\Controllers\HomeController.cs">
</Event><Event ErrorLevel="0" Project="FacebookAzure" Source="FacebookAzure\Controllers\LikesController.cs" Description="File successfully backed up as C:\Code\FacebookAzure\Backup\FacebookAzure\Controllers\LikesController.cs">
</Event><Event ErrorLevel="0" Project="FacebookAzure" Source="FacebookAzure\Global.asax.cs" Description="File successfully backed up as C:\Code\FacebookAzure\Backup\FacebookAzure\Global.asax.cs">
</Event><Event ErrorLevel="0" Project="FacebookAzure" Source="FacebookAzure\Properties\AssemblyInfo.cs" Description="File successfully backed up as C:\Code\FacebookAzure\Backup\FacebookAzure\Properties\AssemblyInfo.cs">
</Event><Event ErrorLevel="0" Project="FacebookAzure" Source="FacebookAzure\Global.asax" Description="File successfully backed up as C:\Code\FacebookAzure\Backup\FacebookAzure\Global.asax">
</Event><Event ErrorLevel="0" Project="FacebookAzure" Source="FacebookAzure\Content\Site.css" Description="File successfully backed up as C:\Code\FacebookAzure\Backup\FacebookAzure\Content\Site.css">
</Event><Event ErrorLevel="0" Project="FacebookAzure" Source="FacebookAzure\Content\themes\base\jquery-ui.css" Description="File successfully backed up as C:\Code\FacebookAzure\Backup\FacebookAzure\Content\themes\base\jquery-ui.css">
</Event><Event ErrorLevel="0" Project="FacebookAzure" Source="FacebookAzure\Content\themes\base\images\ui-bg_flat_0_aaaaaa_40x100.png" Description="File successfully backed up as C:\Code\FacebookAzure\Backup\FacebookAzure\Content\themes\base\images\ui-bg_flat_0_aaaaaa_40x100.png">
</Event><Event ErrorLevel="0" Project="FacebookAzure" Source="FacebookAzure\Content\themes\base\images\ui-bg_flat_75_ffffff_40x100.png" Description="File successfully backed up as C:\Code\FacebookAzure\Backup\FacebookAzure\Content\themes\base\images\ui-bg_flat_75_ffffff_40x100.png">
</Event><Event ErrorLevel="0" Project="FacebookAzure" Source="FacebookAzure\Content\themes\base\images\ui-bg_glass_55_fbf9ee_1x400.png" Description="File successfully backed up as C:\Code\FacebookAzure\Backup\FacebookAzure\Content\themes\base\images\ui-bg_glass_55_fbf9ee_1x400.png">
</Event><Event ErrorLevel="0" Project="FacebookAzure" Source="FacebookAzure\Content\themes\base\images\ui-bg_glass_65_ffffff_1x400.png" Description="File successfully backed up as C:\Code\FacebookAzure\Backup\FacebookAzure\Content\themes\base\images\ui-bg_glass_65_ffffff_1x400.png">
</Event><Event ErrorLevel="0" Project="FacebookAzure" Source="FacebookAzure\Content\themes\base\images\ui-bg_glass_75_dadada_1x400.png" Description="File successfully backed up as C:\Code\FacebookAzure\Backup\FacebookAzure\Content\themes\base\images\ui-bg_glass_75_dadada_1x400.png">
</Event><Event ErrorLevel="0" Project="FacebookAzure" Source="FacebookAzure\Content\themes\base\images\ui-bg_glass_75_e6e6e6_1x400.png" Description="File successfully backed up as C:\Code\FacebookAzure\Backup\FacebookAzure\Content\themes\base\images\ui-bg_glass_75_e6e6e6_1x400.png">
</Event><Event ErrorLevel="0" Project="FacebookAzure" Source="FacebookAzure\Content\themes\base\images\ui-bg_glass_95_fef1ec_1x400.png" Description="File successfully backed up as C:\Code\FacebookAzure\Backup\FacebookAzure\Content\themes\base\images\ui-bg_glass_95_fef1ec_1x400.png">
</Event><Event ErrorLevel="0" Project="FacebookAzure" Source="FacebookAzure\Content\themes\base\images\ui-bg_highlight-soft_75_cccccc_1x100.png" Description="File successfully backed up as C:\Code\FacebookAzure\Backup\FacebookAzure\Content\themes\base\images\ui-bg_highlight-soft_75_cccccc_1x100.png">
</Event><Event ErrorLevel="0" Project="FacebookAzure" Source="FacebookAzure\Content\themes\base\images\ui-icons_222222_256x240.png" Description="File successfully backed up as C:\Code\FacebookAzure\Backup\FacebookAzure\Content\themes\base\images\ui-icons_222222_256x240.png">
</Event><Event ErrorLevel="0" Project="FacebookAzure" Source="FacebookAzure\Content\themes\base\images\ui-icons_2e83ff_256x240.png" Description="File successfully backed up as C:\Code\FacebookAzure\Backup\FacebookAzure\Content\themes\base\images\ui-icons_2e83ff_256x240.png">
</Event><Event ErrorLevel="0" Project="FacebookAzure" Source="FacebookAzure\Content\themes\base\images\ui-icons_454545_256x240.png" Description="File successfully backed up as C:\Code\FacebookAzure\Backup\FacebookAzure\Content\themes\base\images\ui-icons_454545_256x240.png">
</Event><Event ErrorLevel="0" Project="FacebookAzure" Source="FacebookAzure\Content\themes\base\images\ui-icons_888888_256x240.png" Description="File successfully backed up as C:\Code\FacebookAzure\Backup\FacebookAzure\Content\themes\base\images\ui-icons_888888_256x240.png">
</Event><Event ErrorLevel="0" Project="FacebookAzure" Source="FacebookAzure\Content\themes\base\images\ui-icons_cd0a0a_256x240.png" Description="File successfully backed up as C:\Code\FacebookAzure\Backup\FacebookAzure\Content\themes\base\images\ui-icons_cd0a0a_256x240.png">
</Event><Event ErrorLevel="0" Project="FacebookAzure" Source="FacebookAzure\Web.config" Description="File successfully backed up as C:\Code\FacebookAzure\Backup\FacebookAzure\Web.config">
</Event><Event ErrorLevel="0" Project="FacebookAzure" Source="FacebookAzure\Web.Debug.config" Description="File successfully backed up as C:\Code\FacebookAzure\Backup\FacebookAzure\Web.Debug.config">
</Event><Event ErrorLevel="0" Project="FacebookAzure" Source="FacebookAzure\Web.Release.config" Description="File successfully backed up as C:\Code\FacebookAzure\Backup\FacebookAzure\Web.Release.config">
</Event><Event ErrorLevel="0" Project="FacebookAzure" Source="FacebookAzure\Scripts\jquery-1.4.4.js" Description="File successfully backed up as C:\Code\FacebookAzure\Backup\FacebookAzure\Scripts\jquery-1.4.4.js">
</Event><Event ErrorLevel="0" Project="FacebookAzure" Source="FacebookAzure\Scripts\jquery-1.4.4.min.js" Description="File successfully backed up as C:\Code\FacebookAzure\Backup\FacebookAzure\Scripts\jquery-1.4.4.min.js">
</Event><Event ErrorLevel="0" Project="FacebookAzure" Source="FacebookAzure\Scripts\jquery-1.4.4-vsdoc.js" Description="File successfully backed up as C:\Code\FacebookAzure\Backup\FacebookAzure\Scripts\jquery-1.4.4-vsdoc.js">
</Event><Event ErrorLevel="0" Project="FacebookAzure" Source="FacebookAzure\Scripts\jquery.unobtrusive-ajax.js" Description="File successfully backed up as C:\Code\FacebookAzure\Backup\FacebookAzure\Scripts\jquery.unobtrusive-ajax.js">
</Event><Event ErrorLevel="0" Project="FacebookAzure" Source="FacebookAzure\Scripts\jquery.unobtrusive-ajax.min.js" Description="File successfully backed up as C:\Code\FacebookAzure\Backup\FacebookAzure\Scripts\jquery.unobtrusive-ajax.min.js">
</Event><Event ErrorLevel="0" Project="FacebookAzure" Source="FacebookAzure\Scripts\jquery.validate.js" Description="File successfully backed up as C:\Code\FacebookAzure\Backup\FacebookAzure\Scripts\jquery.validate.js">
</Event><Event ErrorLevel="0" Project="FacebookAzure" Source="FacebookAzure\Scripts\jquery.validate.min.js" Description="File successfully backed up as C:\Code\FacebookAzure\Backup\FacebookAzure\Scripts\jquery.validate.min.js">
</Event><Event ErrorLevel="0" Project="FacebookAzure" Source="FacebookAzure\Scripts\jquery.validate.unobtrusive.js" Description="File successfully backed up as C:\Code\FacebookAzure\Backup\FacebookAzure\Scripts\jquery.validate.unobtrusive.js">
</Event><Event ErrorLevel="0" Project="FacebookAzure" Source="FacebookAzure\Scripts\jquery.validate.unobtrusive.min.js" Description="File successfully backed up as C:\Code\FacebookAzure\Backup\FacebookAzure\Scripts\jquery.validate.unobtrusive.min.js">
</Event><Event ErrorLevel="0" Project="FacebookAzure" Source="FacebookAzure\Scripts\jquery.validate-vsdoc.js" Description="File successfully backed up as C:\Code\FacebookAzure\Backup\FacebookAzure\Scripts\jquery.validate-vsdoc.js">
</Event><Event ErrorLevel="0" Project="FacebookAzure" Source="FacebookAzure\Scripts\jquery-ui.js" Description="File successfully backed up as C:\Code\FacebookAzure\Backup\FacebookAzure\Scripts\jquery-ui.js">
</Event><Event ErrorLevel="0" Project="FacebookAzure" Source="FacebookAzure\Scripts\jquery-ui.min.js" Description="File successfully backed up as C:\Code\FacebookAzure\Backup\FacebookAzure\Scripts\jquery-ui.min.js">
</Event><Event ErrorLevel="0" Project="FacebookAzure" Source="FacebookAzure\Scripts\MicrosoftAjax.js" Description="File successfully backed up as C:\Code\FacebookAzure\Backup\FacebookAzure\Scripts\MicrosoftAjax.js">
</Event><Event ErrorLevel="0" Project="FacebookAzure" Source="FacebookAzure\Scripts\MicrosoftAjax.debug.js" Description="File successfully backed up as C:\Code\FacebookAzure\Backup\FacebookAzure\Scripts\MicrosoftAjax.debug.js">
</Event><Event ErrorLevel="0" Project="FacebookAzure" Source="FacebookAzure\Scripts\MicrosoftMvcAjax.js" Description="File successfully backed up as C:\Code\FacebookAzure\Backup\FacebookAzure\Scripts\MicrosoftMvcAjax.js">
</Event><Event ErrorLevel="0" Project="FacebookAzure" Source="FacebookAzure\Scripts\MicrosoftMvcAjax.debug.js" Description="File successfully backed up as C:\Code\FacebookAzure\Backup\FacebookAzure\Scripts\MicrosoftMvcAjax.debug.js">
</Event><Event ErrorLevel="0" Project="FacebookAzure" Source="FacebookAzure\Scripts\MicrosoftMvcValidation.js" Description="File successfully backed up as C:\Code\FacebookAzure\Backup\FacebookAzure\Scripts\MicrosoftMvcValidation.js">
</Event><Event ErrorLevel="0" Project="FacebookAzure" Source="FacebookAzure\Scripts\MicrosoftMvcValidation.debug.js" Description="File successfully backed up as C:\Code\FacebookAzure\Backup\FacebookAzure\Scripts\MicrosoftMvcValidation.debug.js">
</Event><Event ErrorLevel="0" Project="FacebookAzure" Source="FacebookAzure\Views\Web.config" Description="File successfully backed up as C:\Code\FacebookAzure\Backup\FacebookAzure\Views\Web.config">
</Event><Event ErrorLevel="0" Project="FacebookAzure" Source="FacebookAzure\Views\_ViewStart.cshtml" Description="File successfully backed up as C:\Code\FacebookAzure\Backup\FacebookAzure\Views\_ViewStart.cshtml">
</Event><Event ErrorLevel="0" Project="FacebookAzure" Source="FacebookAzure\Views\Shared\Error.cshtml" Description="File successfully backed up as C:\Code\FacebookAzure\Backup\FacebookAzure\Views\Shared\Error.cshtml">
</Event><Event ErrorLevel="0" Project="FacebookAzure" Source="FacebookAzure\Views\Shared\_Layout.cshtml" Description="File successfully backed up as C:\Code\FacebookAzure\Backup\FacebookAzure\Views\Shared\_Layout.cshtml">
</Event><Event ErrorLevel="0" Project="FacebookAzure" Source="FacebookAzure\Views\Home\Index.cshtml" Description="File successfully backed up as C:\Code\FacebookAzure\Backup\FacebookAzure\Views\Home\Index.cshtml">
</Event><Event ErrorLevel="0" Project="FacebookAzure" Source="FacebookAzure\packages.config" Description="File successfully backed up as C:\Code\FacebookAzure\Backup\FacebookAzure\packages.config">
</Event><Event ErrorLevel="0" Project="FacebookAzure" Source="FacebookAzure\Views\Home\PleaseWait.cshtml" Description="File successfully backed up as C:\Code\FacebookAzure\Backup\FacebookAzure\Views\Home\PleaseWait.cshtml">
</Event><Event ErrorLevel="0" Project="FacebookAzure" Source="FacebookAzure\FacebookAzure.csproj" Description="The project file does not require conversion.">
</Event><Event ErrorLevel="3" Project="FacebookAzure" Source="FacebookAzure\FacebookAzure.csproj" Description="No Conversion Required">
</Event><Event ErrorLevel="0" Project="C:\Code\FacebookAzure\FacebookService\FacebookService.ccproj" Source="FacebookService\FacebookService.ccproj" Description="Project file successfully backed up as C:\Code\FacebookAzure\Backup\FacebookService\FacebookService.ccproj">
</Event><Event ErrorLevel="0" Project="C:\Code\FacebookAzure\FacebookService\FacebookService.ccproj" Source="FacebookService\ServiceDefinition.csdef" Description="File successfully backed up as C:\Code\FacebookAzure\Backup\FacebookService\ServiceDefinition.csdef">
</Event><Event ErrorLevel="0" Project="C:\Code\FacebookAzure\FacebookService\FacebookService.ccproj" Source="FacebookService\ServiceConfiguration.cscfg" Description="File successfully backed up as C:\Code\FacebookAzure\Backup\FacebookService\ServiceConfiguration.cscfg">
</Event><Event ErrorLevel="0" Project="C:\Code\FacebookAzure\FacebookService\FacebookService.ccproj" Source="FacebookService\FacebookService.ccproj" Description="Upgraded ProductVersion value to 1.4.0.">
</Event><Event ErrorLevel="0" Project="C:\Code\FacebookAzure\FacebookService\FacebookService.ccproj" Source="FacebookService\FacebookService.ccproj" Description="Upgrade CloudExtensionsDir value to $(MSBuildExtensionsPath)\Microsoft\VisualStudio\v$(VisualStudioVersion)\Windows Azure Tools\1.4\.">
</Event><Event ErrorLevel="0" Project="C:\Code\FacebookAzure\FacebookService\FacebookService.ccproj" Source="FacebookService\FacebookService.ccproj" Description="Upgraded target file name from Microsoft.CloudService.targets to Microsoft.WindowsAzure.targets.">
</Event><Event ErrorLevel="0" Project="C:\Code\FacebookAzure\FacebookService\FacebookService.ccproj" Source="FacebookService\FacebookService.ccproj" Description="Added import $(MSBuildExtensionsPath)\$(MSBuildToolsVersion)\Microsoft.Common.props.">
</Event><Event ErrorLevel="0" Project="C:\Code\FacebookAzure\FacebookService\FacebookService.ccproj" Source="FacebookService\FacebookService.ccproj" Description="Added VisualStudioVersion property.">
</Event><Event ErrorLevel="0" Project="LikerLib" Source="LikerLib\LikerLib.csproj" Description="Project file successfully backed up as C:\Code\FacebookAzure\Backup\LikerLib\LikerLib.csproj">
</Event><Event ErrorLevel="0" Project="LikerLib" Source="LikerLib\FriendLikesContext.cs" Description="File successfully backed up as C:\Code\FacebookAzure\Backup\LikerLib\FriendLikesContext.cs">
</Event><Event ErrorLevel="0" Project="LikerLib" Source="LikerLib\FriendLike.cs" Description="File successfully backed up as C:\Code\FacebookAzure\Backup\LikerLib\FriendLike.cs">
</Event><Event ErrorLevel="0" Project="LikerLib" Source="LikerLib\FriendLikesService.cs" Description="File successfully backed up as C:\Code\FacebookAzure\Backup\LikerLib\FriendLikesService.cs">
</Event><Event ErrorLevel="0" Project="LikerLib" Source="LikerLib\FriendLikeState.cs" Description="File successfully backed up as C:\Code\FacebookAzure\Backup\LikerLib\FriendLikeState.cs">
</Event><Event ErrorLevel="0" Project="LikerLib" Source="LikerLib\Properties\AssemblyInfo.cs" Description="File successfully backed up as C:\Code\FacebookAzure\Backup\LikerLib\Properties\AssemblyInfo.cs">
</Event><Event ErrorLevel="0" Project="LikerLib" Source="LikerLib\packages.config" Description="File successfully backed up as C:\Code\FacebookAzure\Backup\LikerLib\packages.config">
</Event><Event ErrorLevel="0" Project="LikerLib" Source="LikerLib\LikerLib.csproj" Description="The project file does not require conversion.">
</Event><Event ErrorLevel="3" Project="LikerLib" Source="LikerLib\LikerLib.csproj" Description="No Conversion Required">
</Event><Event ErrorLevel="0" Project="FacebookWorker" Source="FacebookWorker\FacebookWorker.csproj" Description="Project file successfully backed up as C:\Code\FacebookAzure\Backup\FacebookWorker\FacebookWorker.csproj">
</Event><Event ErrorLevel="0" Project="FacebookWorker" Source="FacebookWorker\WorkerRole.cs" Description="File successfully backed up as C:\Code\FacebookAzure\Backup\FacebookWorker\WorkerRole.cs">
</Event><Event ErrorLevel="0" Project="FacebookWorker" Source="FacebookWorker\Properties\AssemblyInfo.cs" Description="File successfully backed up as C:\Code\FacebookAzure\Backup\FacebookWorker\Properties\AssemblyInfo.cs">
</Event><Event ErrorLevel="0" Project="FacebookWorker" Source="FacebookWorker\app.config" Description="File successfully backed up as C:\Code\FacebookAzure\Backup\FacebookWorker\app.config">
</Event><Event ErrorLevel="0" Project="FacebookWorker" Source="FacebookWorker\FacebookWorker.csproj" Description="The project file does not require conversion.">
</Event><Event ErrorLevel="3" Project="FacebookWorker" Source="FacebookWorker\FacebookWorker.csproj" Description="No Conversion Required">
</Event><Event ErrorLevel="0" Project="" Source="FacebookAzure.sln" Description="The solution file does not require conversion.">
</Event><Event ErrorLevel="3" Project="" Source="FacebookAzure.sln" Description="No Conversion Required">
</Event></UpgradeLog>